{"commitInfo":{"timestamp":1749755595428,"operation":"WRITE","operationParameters":{"mode":"Append","partitionBy":"[]"},"readVersion":84,"isolationLevel":"Serializable","isBlindAppend":true,"operationMetrics":{"numFiles":"2","numOutputRows":"65536","numOutputBytes":"244717"},"engineInfo":"Apache-Spark/3.5.0 Delta-Lake/3.2.0","txnId":"d8eda8e6-d2bb-458e-8152-b14eca2b6f0a"}}
{"add":{"path":"part-00000-9c9a68e9-222a-43b2-a522-aa0131fccc5a-c000.snappy.parquet","partitionValues":{},"size":120618,"modificationTime":1749755595372,"dataChange":true,"stats":"{\"numRecords\":32768,\"minValues\":{\"region_name\":\"Архангельская область\",\"city_name\":\"Агрыз\",\"cpe_manufacturer_name\":\"Apple\",\"cpe_model_name\":\"Galaxy A10 Dual\",\"url_host\":\"101.ru\",\"cpe_type_cd\":\"smartphone\",\"cpe_model_os_type\":\"Android\",\"price\":2170.0,\"date\":\"2021-06-16T00:00:00.000Z\",\"part_of_day\":\"day\",\"request_cnt\":1,\"user_id\":4555},\"maxValues\":{\"region_name\":\"Челябинская область\",\"city_name\":\"Ялуторовск\",\"cpe_manufacturer_name\":\"Xiaomi\",\"cpe_model_name\":\"iPhone XR\",\"url_host\":\"zvuch.com\",\"cpe_type_cd\":\"smartphone\",\"cpe_model_os_type\":\"iOS\",\"price\":\"NaN\",\"date\":\"2021-08-27T00:00:00.000Z\",\"part_of_day\":\"night\",\"request_cnt\":12,\"user_id\":410525},\"nullCount\":{\"region_name\":0,\"city_name\":0,\"cpe_manufacturer_name\":0,\"cpe_model_name\":0,\"url_host\":0,\"cpe_type_cd\":0,\"cpe_model_os_type\":0,\"price\":0,\"date\":0,\"part_of_day\":0,\"request_cnt\":0,\"user_id\":0}}"}}
{"add":{"path":"part-00001-5e4239e8-7316-4e7d-ac22-cd4367eb7af0-c000.snappy.parquet","partitionValues":{},"size":124099,"modificationTime":1749755595406,"dataChange":true,"stats":"{\"numRecords\":32768,\"minValues\":{\"region_name\":\"Владимирская область\",\"city_name\":\"Азов\",\"cpe_manufacturer_name\":\"Apple\",\"cpe_model_name\":\"Galaxy A10 Dual\",\"url_host\":\"1000.menu\",\"cpe_type_cd\":\"smartphone\",\"cpe_model_os_type\":\"Android\",\"price\":990.0,\"date\":\"2021-06-16T00:00:00.000Z\",\"part_of_day\":\"day\",\"request_cnt\":1,\"user_id\":15231},\"maxValues\":{\"region_name\":\"Ярославская область\",\"city_name\":\"Ярославль\",\"cpe_manufacturer_name\":\"Xiaomi\",\"cpe_model_name\":\"iPhone XR\",\"url_host\":\"zvuk.com\",\"cpe_type_cd\":\"smartphone\",\"cpe_model_os_type\":\"iOS\",\"price\":113155.0,\"date\":\"2022-06-17T00:00:00.000Z\",\"part_of_day\":\"night\",\"request_cnt\":12,\"user_id\":403344},\"nullCount\":{\"region_name\":0,\"city_name\":0,\"cpe_manufacturer_name\":0,\"cpe_model_name\":0,\"url_host\":0,\"cpe_type_cd\":0,\"cpe_model_os_type\":0,\"price\":0,\"date\":0,\"part_of_day\":0,\"request_cnt\":0,\"user_id\":0}}"}}
